pydpf/Kalman.py
pydpf/__init__.py
pydpf/base.py
pydpf/conditional_resampling.py
pydpf/datautils.py
pydpf/deserialisation.py
pydpf/filtering.py
pydpf/gradient_regularisation.py
pydpf/model_based_api.py
pydpf/optimal_transport.py
pydpf/outputs.py
pydpf/resampling.py
pydpf/utils.py
pydpf/distributions/Gaussian.py
pydpf/distributions/__init__.py
pydpf/distributions/base.py
pydpf/distributions/kde.py
pydpf/distributions/vonMises.py
pydpf-1.1.0.dist-info/METADATA
pydpf-1.1.0.dist-info/WHEEL
pydpf-1.1.0.dist-info/licenses/LICENSE
pydpf-1.1.0.dist-info/RECORD
