Metadata-Version: 2.4
Name: pydpf
Version: 1.1.0
Summary: A package for differentiable particle filtering
Author-email: John-Joseph Brady <john-joseph.brady@kcl.ac.uk>, Benjamin Cox <benjamin.cox@ed.ac.uk>
License: MIT License
License-File: LICENSE
Requires-Python: >=3.12
Requires-Dist: joblib>=1.4.2
Requires-Dist: numpy>=1.26.4
Requires-Dist: numpydoc>=1.7.0
Requires-Dist: pandas>=2.2.2
Requires-Dist: polars>=1.10
Requires-Dist: torch>=2.3.1
Requires-Dist: torchaudio>=2.3.1
Requires-Dist: torchvision>=0.18.1
Provides-Extra: data-preprocessing
Requires-Dist: fastexcel; extra == 'data-preprocessing'
